{
    "params": {
        "--clip-norm": 0.005798601420117899,
        "--dropout": 0.3893200800719538,
        "--label-smoothing": 0.14492862498467357,
        "--lr": 2.0403535591339072e-05,
        "--max-lr": 0.00039498305941538354,
        "--t-mult": 0.5589380103631089,
        "--warmup-updates": 30926.75272813854,
        "--weight-decay": 0.0007135898340953802
    },
    "trial_id": "5e59324d",
    "philly_id": "1553675282044_3480",
    "cluster": "wu3",
    "vc": "msrmt",
    "status": "finished",
    "target": -12.267
}